django_migrate_sql/__init__.py
django_migrate_sql/autodetector.py
django_migrate_sql/config.py
django_migrate_sql/graph.py
django_migrate_sql/operations.py
django_migrate_sql/management/__init__.py
django_migrate_sql/management/commands/__init__.py
django_migrate_sql/management/commands/makemigrations.py
django_migrate_sql/management/commands/migrate.py
django_migrate_sql_deux-1.4.0.dist-info/licenses/LICENSE
django_migrate_sql_deux-1.4.0.dist-info/METADATA
django_migrate_sql_deux-1.4.0.dist-info/WHEEL
django_migrate_sql_deux-1.4.0.dist-info/top_level.txt
django_migrate_sql_deux-1.4.0.dist-info/RECORD
