Metadata-Version: 2.4
Name: django-migrate-sql-deux
Version: 1.4.0
Summary: Django Migrations for raw SQL
Author-email: Bogdan Klichuk <klichukb@gmail.com>, Bruno Alla <oss@browniebroke.com>
License-Expression: ISC
Project-URL: Bug Tracker, https://github.com/browniebroke/django-migrate-sql-deux/issues
Project-URL: Changelog, https://github.com/browniebroke/django-migrate-sql-deux/blob/main/CHANGELOG.md
Project-URL: repository, https://github.com/browniebroke/django-migrate-sql-deux
Classifier: Development Status :: 5 - Production/Stable
Classifier: Intended Audience :: Developers
Classifier: Natural Language :: English
Classifier: Operating System :: OS Independent
Classifier: Framework :: Django
Classifier: Framework :: Django :: 4.2
Classifier: Framework :: Django :: 5.0
Classifier: Framework :: Django :: 5.1
Classifier: Framework :: Django :: 5.2
Classifier: Framework :: Django :: 6.0
Classifier: Programming Language :: Python :: 3.10
Classifier: Programming Language :: Python :: 3.11
Classifier: Programming Language :: Python :: 3.12
Classifier: Programming Language :: Python :: 3.13
Classifier: Programming Language :: Python :: 3.14
Classifier: Topic :: Software Development :: Libraries
Requires-Python: >=3.10
License-File: LICENSE
Requires-Dist: django>=4.2
Dynamic: license-file
